setup.py
onetools/__init__.py
onetools/decorator.py
onetools/mysql.py
onetools/restful.py
onetools.egg-info/PKG-INFO
onetools.egg-info/SOURCES.txt
onetools.egg-info/dependency_links.txt
onetools.egg-info/top_level.txt