Metadata-Version: 1.0
Name: onetools
Version: 0.1.0
Summary: chandler tool
Home-page: https://github.com/chandlercjy
Author: ChandlerChan
Author-email: chenjiayicjy@126.com
License: MIT Licence
Keywords: pip,mysql
Platform: any
